[
  {
    "timestamp": "2025-07-29T19:17:37.325Z",
    "atividade_desejada": "Violão",
    "pagaria": "sim",
    "valor_justo": "51-100",
    "ja_teve_aula": "nao",
    "como_encontrar": [
      "google",
      "indicacao"
    ],
    "comentarios": "Gostaria de encontrar um instrutor qualificado e com boa didática para aprender violão do zero."
  },
  {
    "timestamp": "2025-07-30T02:30:11.430Z",
    "atividade_desejada": "Teste",
    "pagaria": "sim",
    "valor_justo": "101-150",
    "ja_teve_aula": "nao",
    "como_encontrar": [
      "indicacao"
    ],
    "comentarios": "teste"
  }
]